sofia_redux/__init__.py
sofia_redux/_astropy_init.py
sofia_redux/conftest.py
sofia_redux/version.py
sofia_redux/calibration/__init__.py
sofia_redux/calibration/_astropy_init.py
sofia_redux/calibration/conftest.py
sofia_redux/calibration/pipecal_applyphot.py
sofia_redux/calibration/pipecal_calfac.py
sofia_redux/calibration/pipecal_config.py
sofia_redux/calibration/pipecal_error.py
sofia_redux/calibration/pipecal_fitpeak.py
sofia_redux/calibration/pipecal_photometry.py
sofia_redux/calibration/pipecal_rratio.py
sofia_redux/calibration/pipecal_util.py
sofia_redux/calibration/version.py
sofia_redux/calibration/data/README.rst
sofia_redux/calibration/data/flitecam/caldefault.txt
sofia_redux/calibration/data/flitecam/stddefault.txt
sofia_redux/calibration/data/flitecam/filter_def/filter_def_20140227.txt
sofia_redux/calibration/data/flitecam/ref_calfctr/refcalfac_20140227.txt
sofia_redux/calibration/data/flitecam/ref_calfctr/refcalfac_20151002.txt
sofia_redux/calibration/data/flitecam/ref_calfctr/refcalfac_20161020.txt
sofia_redux/calibration/data/flitecam/ref_calfctr/refcalfac_20171007.txt
sofia_redux/calibration/data/flitecam/response/rfit_alt_flipo_20140227.txt
sofia_redux/calibration/data/flitecam/response/rfit_alt_noflipo_20140227.txt
sofia_redux/calibration/data/flitecam/response/rfit_am_flipo_20140227.txt
sofia_redux/calibration/data/flitecam/response/rfit_am_noflipo_20140227.txt
sofia_redux/calibration/data/flitecam/response/rfit_pwv_flipo_20140227.txt
sofia_redux/calibration/data/flitecam/response/rfit_pwv_noflipo_20140227.txt
sofia_redux/calibration/data/flitecam/standard_flux/HD118280_calib.out
sofia_redux/calibration/data/flitecam/standard_flux/HD118280_calib_FLIPO.out
sofia_redux/calibration/data/flitecam/standard_flux/HD118290_calib.out
sofia_redux/calibration/data/flitecam/standard_flux/HD118290_calib_FLIPO.out
sofia_redux/calibration/data/flitecam/standard_flux/HD139308_calib.out
sofia_redux/calibration/data/flitecam/standard_flux/HD139308_calib_FLIPO.out
sofia_redux-1.1.1.dist-info/LICENSE.rst
sofia_redux-1.1.1.dist-info/METADATA
sofia_redux-1.1.1.dist-info/WHEEL
sofia_redux-1.1.1.dist-info/entry_points.txt
sofia_redux-1.1.1.dist-info/top_level.txt
sofia_redux-1.1.1.dist-info/RECORD
