Metadata-Version: 2.1
Name: sofia-redux
Version: 1.1.1
Summary: SOFIA data reduction pipelines
Home-page: https://github.com/SOFIA-USRA/sofia_redux
Author: SOFIA-USRA
Author-email: mclarke@sofia.usra.edu
License: BSD 3-Clause
Keywords: astronomy,astrophysics,space,science,sofia,observatory,infrared,imaging,spectroscopy,polarimetry
Platform: UNKNOWN
Classifier: Intended Audience :: Science/Research
Classifier: License :: OSI Approved :: BSD License
Classifier: Operating System :: OS Independent
Classifier: Programming Language :: Python :: 3
Classifier: Programming Language :: Python :: Implementation :: CPython
Classifier: Topic :: Scientific/Engineering :: Astronomy
Requires-Python: >=3.8
License-File: licenses/LICENSE.rst
Requires-Dist: astropy (>=4.0)
Requires-Dist: astroquery (>=0.4.4)
Requires-Dist: bottleneck (>=1.3.1)
Requires-Dist: cloudpickle (>=1.6.0)
Requires-Dist: configobj (>=5)
Requires-Dist: cycler (>=0.10.0)
Requires-Dist: dill (>=0.3)
Requires-Dist: graphviz (>=0.16)
Requires-Dist: joblib (>=0.14.1)
Requires-Dist: matplotlib (>=3.3)
Requires-Dist: more-itertools (>=8.5.0)
Requires-Dist: numba (>=0.53.1)
Requires-Dist: numpy (>=1.20.0)
Requires-Dist: pandas (>=1.0.1)
Requires-Dist: photutils (>=0.7.2)
Requires-Dist: psutil (>=5.8.0)
Requires-Dist: scikit-image (<0.19)
Requires-Dist: scikit-learn (>=0.22.1)
Requires-Dist: scipy (>=1.4.1)
Provides-Extra: all
Requires-Dist: PyQt5 (>=5.9.2) ; extra == 'all'
Requires-Dist: pytest-qt (>=3.3.0) ; extra == 'all'
Requires-Dist: pyds9 (>=1.8.1) ; extra == 'all'
Requires-Dist: regions (>=0.5) ; extra == 'all'
Provides-Extra: docs
Requires-Dist: sphinx-astropy (>=1.2) ; extra == 'docs'
Provides-Extra: test
Requires-Dist: pytest (>=5.3.5) ; extra == 'test'
Requires-Dist: pytest-astropy (>=0.8.0) ; extra == 'test'
Requires-Dist: pytest-astropy-header (>=0.1.2) ; extra == 'test'
Requires-Dist: pytest-cov (>=2.8.1) ; extra == 'test'
Requires-Dist: pytest-mock (>=1.13.0) ; extra == 'test'
Requires-Dist: pytest-remotedata (>=0.3.2) ; extra == 'test'
Requires-Dist: pytest-timeout (>=1.3.3) ; extra == 'test'
